odoo/addons/l10n_ro_account_period_close/README.rst
odoo/addons/l10n_ro_account_period_close/__init__.py
odoo/addons/l10n_ro_account_period_close/__manifest__.py
odoo/addons/l10n_ro_account_period_close/i18n/l10n_ro_account_period_close.pot
odoo/addons/l10n_ro_account_period_close/models/__init__.py
odoo/addons/l10n_ro_account_period_close/models/account.py
odoo/addons/l10n_ro_account_period_close/models/account_period_close.py
odoo/addons/l10n_ro_account_period_close/security/account_security.xml
odoo/addons/l10n_ro_account_period_close/security/ir.model.access.csv
odoo/addons/l10n_ro_account_period_close/static/description/icon.png
odoo/addons/l10n_ro_account_period_close/tests/__init__.py
odoo/addons/l10n_ro_account_period_close/tests/test_period_closing.py
odoo/addons/l10n_ro_account_period_close/views/account_period_close_view.xml
odoo/addons/l10n_ro_account_period_close/wizards/__init__.py
odoo/addons/l10n_ro_account_period_close/wizards/wizard_account_period_closing.py
odoo/addons/l10n_ro_account_period_close/wizards/wizard_account_period_closing_view.xml
odoo11_addon_l10n_ro_account_period_close-11.0.1.0.0.99.dev10.dist-info/METADATA
odoo11_addon_l10n_ro_account_period_close-11.0.1.0.0.99.dev10.dist-info/WHEEL
odoo11_addon_l10n_ro_account_period_close-11.0.1.0.0.99.dev10.dist-info/top_level.txt
odoo11_addon_l10n_ro_account_period_close-11.0.1.0.0.99.dev10.dist-info/RECORD
